Metadata-Version: 1.1
Name: rltg
Version: 0.1.2.post1
Summary: Framework for Reinforcement Learning with Temporal Goals.
Home-page: https://github.com/MarcoFavorito/rltg
Author: Marco Favorito
Author-email: marco.favorito@gmail.com
License: MIT license
Keywords: rltg
Platform: UNKNOWN
Classifier: Development Status :: 2 - Pre-Alpha
Classifier: Intended Audience :: Developers
Classifier: License :: OSI Approved :: MIT License
Classifier: Natural Language :: English
Classifier: Programming Language :: Python :: 3.5
Classifier: Programming Language :: Python :: 3.6
